[
    {
        "category": "Machine Learning",
        "name": "PyTorch",
        "percentage": 75,
        "logo":"/logos/pytorch.png"
    },
    {
        "category": "Machine Learning",
        "name": "Hugging Face",
        "percentage": 70,
        "logo":"/logos/huggingface.svg"
    },
    {
        "category": "Data Science",
        "name": "NumPy",
        "percentage": 80,
        "logo":"/logos/numpy.svg"
    },
    {
        "category": "Programming Languages",
        "name": "JavaScript",
        "percentage": 90,
        "logo":"/logos/js.png"
    },
    {
        "category": "Programming Languages",
        "name": "Python",
        "percentage": 85,
        "logo":"/logos/python.png"
    },
    {
        "category": "Programming Languages",
        "name": "TypeScript",
        "percentage": 80,
        "logo":"/logos/ts.png"
    },
    {
        "category": "Frontend",
        "name": "React",
        "percentage": 90,
        "logo":"/logos/react.png"
    },
    {
        "category": "Frontend",
        "name": "Next.js",
        "percentage": 98,
        "logo":"/logos/nextjs.png"
    },
    {
        "category": "Frontend",
        "name": "HTML5/CSS3",
        "percentage": 95,
        "logo":"/logos/html.png"
    },
    {
        "category": "Frontend",
        "name": "Tailwind CSS",
        "percentage": 95,
        "logo":"/logos/tailwind.png"
    },
    {
        "category": "Backend",
        "name": "Node.js",
        "percentage": 85,
        "logo":"/logos/node.png"       
    },
    {
        "category": "Backend",
        "name": "Express",
        "percentage": 80,
        "logo":"/logos/express.png"  
    },
    {
        "category": "Database",
        "name": "MongoDB",
        "percentage": 75,
        "logo":"/logos/mongodb.png"
    },
    {
        "category": "Database",
        "name": "PostgreSQL",
        "percentage": 70,
        "logo":"/logos/postgresql.png"
    },
    {
        "category": "DevOps",
        "name": "Docker",
        "percentage": 65,
        "logo":"/logos/docker.png"
    },
    {
        "category": "DevOps",
        "name": "Git",
        "percentage": 90,
        "logo":"/logos/git.png"
    },
    {
        "category": "Design",
        "name": "Figma",
        "percentage": 60,
        "logo":"/logos/figma.png"
    }
]